[
    {
        "match_time": "1735480800",
        "match_status": "live",
        "home_team_name": "Napoli",
        "home_team_logo": "https://sta.vnres.co/file/common/20241225/f9c113bc0688b859dbfceae60f113bbf.png",
        "away_team_name": "Venezia",
        "away_team_logo": "https://sta.vnres.co/file/common/20241225/73f8ac2742693fb4ed8b52dc982d708f.png",
        "league_name": "ITA D1",
        "servers": [
            {
                "name": "Soco SD",
                "stream_url": "https://pull.niur.live/live/stream-235232_lsd.m3u8?txSecret=87a3dcb3512daf34fdcf9d0bb3606e40&txTime=6772bbeb",
                "referer": "https://socolivev.co/"
            },
            {
                "name": "Soco HD",
                "stream_url": "https://pull.niur.live/live/stream-235232_lhd.m3u8?txSecret=095ee0004926f71c84b71d61d65e9a17&txTime=6772bbeb",
                "referer": "https://socolivev.co/"
            },
            {
                "name": "Soco SD",
                "stream_url": "https://pull.niur.live/live/stream-364855_lsd.m3u8?txSecret=0354ebf37bbb60dcc8c2e8020e423fa0&txTime=6772bb73",
                "referer": "https://socolivev.co/"
            },
            {
                "name": "Soco HD",
                "stream_url": "https://pull.niur.live/live/stream-364855_lhd.m3u8?txSecret=4f0460adfade41e2616dc37eb92ef3ed&txTime=6772bb73",
                "referer": "https://socolivev.co/"
            },
            {
                "name": "Soco SD",
                "stream_url": "https://pull.niues.live/live/stream-9912035_lsd.m3u8?auth_key=1735554347-0-0-71df6423af893c0aff62a79ccbb4d811",
                "referer": "https://socolivev.co/"
            },
            {
                "name": "Soco HD",
                "stream_url": "https://pull.niues.live/live/stream-9912035_lhd.m3u8?auth_key=1735554347-0-0-dd24df77f129e1e0fe68db2e28a7280b",
                "referer": "https://socolivev.co/"
            },
            {
                "name": "Soco SD",
                "stream_url": "https://pull.niues.live/live/stream-9911957_lsd.m3u8?auth_key=1735574257-0-0-fb4b87cf9b97dbac3a8a581603ba15b5",
                "referer": "https://socolivev.co/"
            },
            {
                "name": "Soco HD",
                "stream_url": "https://pull.niues.live/live/stream-9911957_lhd.m3u8?auth_key=1735574257-0-0-44742b38b2845b9702ce9c5761b59d15",
                "referer": "https://socolivev.co/"
            },
            {
                "name": "Soco SD",
                "stream_url": "https://pull.niues.live/live/stream-239275_lsd.m3u8?auth_key=1735515020-0-0-14c87bd70968778e1e540a2639c4ecd8",
                "referer": "https://socolivev.co/"
            },
            {
                "name": "Soco HD",
                "stream_url": "https://pull.niues.live/live/stream-239275_lhd.m3u8?auth_key=1735515020-0-0-5688f6db49748ef0725c659dbe0788cf",
                "referer": "https://socolivev.co/"
            },
            {
                "name": "Soco SD",
                "stream_url": "https://pull.niur.live/live/stream-283501_lsd.m3u8?txSecret=5e8d8ea2b5596ae437db5b4f5d333167&txTime=67723b47",
                "referer": "https://socolivev.co/"
            },
            {
                "name": "Soco HD",
                "stream_url": "https://pull.niur.live/live/stream-283501_lhd.m3u8?txSecret=a9bfee2e4e74f7cd79b4746141c9f4cb&txTime=67723b47",
                "referer": "https://socolivev.co/"
            }
        ]
    },
    {
        "match_time": "1735480800",
        "match_status": "live",
        "home_team_name": "Jamshedpur FC",
        "home_team_logo": "https://sta.vnres.co/file/common/20241225/119cf3ba91fb5fbe2b62ae601206c3a6.png",
        "away_team_name": "Kerala Blasters FC",
        "away_team_logo": "https://sta.vnres.co/file/common/20241225/6adfe2677012753f111e0dbbb291009c.png",
        "league_name": "IND SL",
        "servers": [
            {
                "name": "Soco SD",
                "stream_url": "https://pull.niues.live/live/stream-9912016_lsd.m3u8?auth_key=1735574359-0-0-e79658e627cadcaafce600ded3fa0044",
                "referer": "https://socolivev.co/"
            },
            {
                "name": "Soco HD",
                "stream_url": "https://pull.niues.live/live/stream-9912016_lhd.m3u8?auth_key=1735574359-0-0-277397a8a0c84926010dfbfd7ae762c6",
                "referer": "https://socolivev.co/"
            },
            {
                "name": "Soco SD",
                "stream_url": "https://pull.niues.live/live/stream-380460_lsd.m3u8?auth_key=1735574673-0-0-29e1b94cff6ef4e639a3b894976a58bd",
                "referer": "https://socolivev.co/"
            },
            {
                "name": "Soco HD",
                "stream_url": "https://pull.niues.live/live/stream-380460_lhd.m3u8?auth_key=1735574673-0-0-2fb123ae4ad41ba1c94650e4dbf30207",
                "referer": "https://socolivev.co/"
            }
        ]
    },
    {
        "match_time": "1735482600",
        "match_status": "live",
        "home_team_name": "Leicester City",
        "home_team_logo": "https://sta.vnres.co/file/common/20241225/2422ece8538b4fea5d6c715e208512eb.png",
        "away_team_name": "Manchester City",
        "away_team_logo": "https://sta.vnres.co/file/common/20241225/69016862e4e0235172ed8412a930dfec.png",
        "league_name": "ENG PR",
        "servers": [
            {
                "name": "Soco SD",
                "stream_url": "https://pull.niur.live/live/stream-9912009_lsd.m3u8?txSecret=b9bf33979a4a432f1fe88f570a54b91f&txTime=67730ae1",
                "referer": "https://socolivev.co/"
            },
            {
                "name": "Soco HD",
                "stream_url": "https://pull.niur.live/live/stream-9912009_lhd.m3u8?txSecret=a20fa77469ff2068c20bec7ab7316ab8&txTime=67730ae1",
                "referer": "https://socolivev.co/"
            },
            {
                "name": "Soco SD",
                "stream_url": "https://pull.niues.live/live/stream-9912008_lsd.m3u8?auth_key=1735574673-0-0-ceee009149691dba6cb8853c4a896aa2",
                "referer": "https://socolivev.co/"
            },
            {
                "name": "Soco HD",
                "stream_url": "https://pull.niues.live/live/stream-9912008_lhd.m3u8?auth_key=1735574673-0-0-51b9596d05476a28e89cec0e93ece23d",
                "referer": "https://socolivev.co/"
            },
            {
                "name": "Soco SD",
                "stream_url": "https://pull.niues.live/live/stream-9912077_lsd.m3u8?auth_key=1735512148-0-0-cee29c573f7e53a270596359bf9b6922",
                "referer": "https://socolivev.co/"
            },
            {
                "name": "Soco HD",
                "stream_url": "https://pull.niues.live/live/stream-9912077_lhd.m3u8?auth_key=1735512148-0-0-6905b28619bcd4724289630d929fa9a6",
                "referer": "https://socolivev.co/"
            },
            {
                "name": "Soco SD",
                "stream_url": "https://pull.niur.live/live/stream-9912102_lsd.m3u8?txSecret=f5c43f8f26fa78c937e52bfd85920a3b&txTime=6772bc44",
                "referer": "https://socolivev.co/"
            },
            {
                "name": "Soco HD",
                "stream_url": "https://pull.niur.live/live/stream-9912102_lhd.m3u8?txSecret=43dd5f69cdb8663022d21cf89cd2b317&txTime=6772bc44",
                "referer": "https://socolivev.co/"
            },
            {
                "name": "Soco SD",
                "stream_url": "https://pull.niur.live/live/stream-9911977_lsd.m3u8?txSecret=e125e5d1c2bece10dc27dde3f0a3fd2e&txTime=6772185f",
                "referer": "https://socolivev.co/"
            },
            {
                "name": "Soco HD",
                "stream_url": "https://pull.niur.live/live/stream-9911977_lhd.m3u8?txSecret=b2d3b23a17336ab6205f7f3b85358356&txTime=6772185f",
                "referer": "https://socolivev.co/"
            },
            {
                "name": "Soco SD",
                "stream_url": "https://pull.niues.live/live/stream-351530_lsd.m3u8?auth_key=1735512438-0-0-5b2ba718cea00a7ff0069acf7070e1dc",
                "referer": "https://socolivev.co/"
            },
            {
                "name": "Soco HD",
                "stream_url": "https://pull.niues.live/live/stream-351530_lhd.m3u8?auth_key=1735512438-0-0-92367e87568a8b5c9324d639afde6347",
                "referer": "https://socolivev.co/"
            }
        ]
    },
    {
        "match_time": "1735484400",
        "match_status": "live",
        "home_team_name": "Celtic FC",
        "home_team_logo": "https://sta.vnres.co/file/common/20241225/b99c3af85600435b5568bed19133f0dd.png",
        "away_team_name": "Saint Johnstone",
        "away_team_logo": "https://sta.vnres.co/file/common/20241225/b753c3da14ad6ae5f9d05b4ab5b88dce.png",
        "league_name": "SCO PR",
        "servers": [
            {
                "name": "Soco SD",
                "stream_url": "https://pull.niues.live/live/stream-9912043_lsd.m3u8?auth_key=1735504844-0-0-c4ba2f7178d498658fa707a6a0e68108",
                "referer": "https://socolivev.co/"
            },
            {
                "name": "Soco HD",
                "stream_url": "https://pull.niues.live/live/stream-9912043_lhd.m3u8?auth_key=1735504844-0-0-41c202ef1c73c3179dd3445e5d202388",
                "referer": "https://socolivev.co/"
            },
            {
                "name": "Soco SD",
                "stream_url": "https://pull.niues.live/live/stream-459401_lsd.m3u8?auth_key=1735503553-0-0-21bac911f0d29fa4abc0a72f743471e1",
                "referer": "https://socolivev.co/"
            },
            {
                "name": "Soco HD",
                "stream_url": "https://pull.niues.live/live/stream-459401_lhd.m3u8?auth_key=1735503553-0-0-95097293051af14b24be3b8ca36c72c7",
                "referer": "https://socolivev.co/"
            },
            {
                "name": "Soco SD",
                "stream_url": "https://pull.niues.live/live/stream-371450_lsd.m3u8?auth_key=1735574673-0-0-b022b0f74518f312d33125bef20553a4",
                "referer": "https://socolivev.co/"
            },
            {
                "name": "Soco HD",
                "stream_url": "https://pull.niues.live/live/stream-371450_lhd.m3u8?auth_key=1735574673-0-0-f01f0700cbd6ff8de7218c40a6088697",
                "referer": "https://socolivev.co/"
            }
        ]
    },
    {
        "match_time": "1735484400",
        "match_status": "live",
        "home_team_name": "Motherwell",
        "home_team_logo": "https://sta.vnres.co/file/common/20241225/31d415ffeab3942f786ab795159624c4.png",
        "away_team_name": "Glasgow Rangers",
        "away_team_logo": "https://sta.vnres.co/file/common/20241225/a0317b06ba7a60e994189c9b7a6d69c1.png",
        "league_name": "SCO PR",
        "servers": [
            {
                "name": "Soco SD",
                "stream_url": "https://pull.niues.live/live/stream-308080_lsd.m3u8?auth_key=1735504988-0-0-2d17b47800ac454b465232d4bd5dd3a2",
                "referer": "https://socolivev.co/"
            },
            {
                "name": "Soco HD",
                "stream_url": "https://pull.niues.live/live/stream-308080_lhd.m3u8?auth_key=1735504988-0-0-fc36d609dbd7c1881b97652fdf4294b0",
                "referer": "https://socolivev.co/"
            },
            {
                "name": "Soco SD",
                "stream_url": "https://pull.niur.live/live/stream-9912092_lsd.m3u8?txSecret=45909e48cd285da4bd98eaa134bd0c64&txTime=6771fa7f",
                "referer": "https://socolivev.co/"
            },
            {
                "name": "Soco HD",
                "stream_url": "https://pull.niur.live/live/stream-9912092_lhd.m3u8?txSecret=92e6b27311c0eb1cd6cbcabce360b005&txTime=6771fa7f",
                "referer": "https://socolivev.co/"
            },
            {
                "name": "Soco SD",
                "stream_url": "https://pull.niur.live/live/stream-991117_lsd.m3u8?txSecret=eb502637d740fef7be9ddab14f21d981&txTime=677238a3",
                "referer": "https://socolivev.co/"
            },
            {
                "name": "Soco HD",
                "stream_url": "https://pull.niur.live/live/stream-991117_lhd.m3u8?txSecret=9409ab2411ad7a25c32edfd7fa552bb2&txTime=677238a3",
                "referer": "https://socolivev.co/"
            }
        ]
    },
    {
        "match_time": "1735484400",
        "match_status": "live",
        "home_team_name": "Crystal Palace",
        "home_team_logo": "https://sta.vnres.co/file/common/20241225/46b9d615227b81ec66fb7dd9afc7ba2e.png",
        "away_team_name": "Southampton",
        "away_team_logo": "https://sta.vnres.co/file/common/20241225/1127f1945a4eac3606e5374a2fea29da.png",
        "league_name": "ENG PR",
        "servers": [
            {
                "name": "Soco SD",
                "stream_url": "https://pull.niues.live/live/stream-313971_lsd.m3u8?auth_key=1735574673-0-0-8beb5e896c8b9f669d214aec0f7cc907",
                "referer": "https://socolivev.co/"
            },
            {
                "name": "Soco HD",
                "stream_url": "https://pull.niues.live/live/stream-313971_lhd.m3u8?auth_key=1735574673-0-0-61ec2dffd5d280b954100ef556b7b0e3",
                "referer": "https://socolivev.co/"
            },
            {
                "name": "Soco SD",
                "stream_url": "https://pull.niues.live/live/stream-344370_lsd.m3u8?auth_key=1735512240-0-0-b28ef24709a65fba6ea73a18ce99d688",
                "referer": "https://socolivev.co/"
            },
            {
                "name": "Soco HD",
                "stream_url": "https://pull.niues.live/live/stream-344370_lhd.m3u8?auth_key=1735512240-0-0-b14f8d06a373c2dbc595839a5291e6d4",
                "referer": "https://socolivev.co/"
            },
            {
                "name": "Soco SD",
                "stream_url": "https://pull.niues.live/live/stream-479849_lsd.m3u8?auth_key=1735574673-0-0-dc460c325e498128411c34e0a1b804bc",
                "referer": "https://socolivev.co/"
            },
            {
                "name": "Soco HD",
                "stream_url": "https://pull.niues.live/live/stream-479849_lhd.m3u8?auth_key=1735574673-0-0-57eea777f5d7e5f304037325dcf99dc6",
                "referer": "https://socolivev.co/"
            },
            {
                "name": "Soco SD",
                "stream_url": "https://pull.niues.live/live/stream-9912097_lsd.m3u8?auth_key=1735574673-0-0-d6cfc991ce4182f874646eb2e8232131",
                "referer": "https://socolivev.co/"
            },
            {
                "name": "Soco HD",
                "stream_url": "https://pull.niues.live/live/stream-9912097_lhd.m3u8?auth_key=1735574673-0-0-4b407952457e6b9a9dd58e27edf3db19",
                "referer": "https://socolivev.co/"
            },
            {
                "name": "Soco SD",
                "stream_url": "https://pull.niues.live/live/stream-434982_lsd.m3u8?auth_key=1735574673-0-0-5027a6813665d99694256c88b5d2fae1",
                "referer": "https://socolivev.co/"
            },
            {
                "name": "Soco HD",
                "stream_url": "https://pull.niues.live/live/stream-434982_lhd.m3u8?auth_key=1735574673-0-0-5e5459d6afaca81b130ad0cea802a009",
                "referer": "https://socolivev.co/"
            },
            {
                "name": "Soco SD",
                "stream_url": "https://pull.niues.live/live/stream-472241_lsd.m3u8?auth_key=1735574673-0-0-d388daa430a6458131d61ff993c67514",
                "referer": "https://socolivev.co/"
            },
            {
                "name": "Soco HD",
                "stream_url": "https://pull.niues.live/live/stream-472241_lhd.m3u8?auth_key=1735574673-0-0-51489655a65210f66031374baffa5225",
                "referer": "https://socolivev.co/"
            }
        ]
    },
    {
        "match_time": "1735484400",
        "match_status": "live",
        "home_team_name": "Everton",
        "home_team_logo": "https://sta.vnres.co/file/common/20241225/1998f1bad987fc9b75481fb0ca514227.png",
        "away_team_name": "Nottingham Forest",
        "away_team_logo": "https://sta.vnres.co/file/common/20241225/dcb21110f9f0ab4f98905d49aec3970f.png",
        "league_name": "ENG PR",
        "servers": [
            {
                "name": "Soco SD",
                "stream_url": "https://pull.niues.live/live/stream-299144_lsd.m3u8?auth_key=1735574673-0-0-e80c51c9ed5721db3625de54db7a9c68",
                "referer": "https://socolivev.co/"
            },
            {
                "name": "Soco HD",
                "stream_url": "https://pull.niues.live/live/stream-299144_lhd.m3u8?auth_key=1735574673-0-0-238e701fd9b398b8e864c37bb56d0dc3",
                "referer": "https://socolivev.co/"
            },
            {
                "name": "Soco SD",
                "stream_url": "https://pull.niues.live/live/stream-414317_lsd.m3u8?auth_key=1735574673-0-0-f393c419ba530a181030558480e6815a",
                "referer": "https://socolivev.co/"
            },
            {
                "name": "Soco HD",
                "stream_url": "https://pull.niues.live/live/stream-414317_lhd.m3u8?auth_key=1735574673-0-0-616b22ef00ec71baabf451e40a1cf36f",
                "referer": "https://socolivev.co/"
            },
            {
                "name": "Soco SD",
                "stream_url": "https://pull.niues.live/live/stream-9912015_lsd.m3u8?auth_key=1735574673-0-0-25c8344fb2c8bf76477a4bbfadb2cf36",
                "referer": "https://socolivev.co/"
            },
            {
                "name": "Soco HD",
                "stream_url": "https://pull.niues.live/live/stream-9912015_lhd.m3u8?auth_key=1735574673-0-0-6b9778a83705bc3c19223d600ea621f2",
                "referer": "https://socolivev.co/"
            },
            {
                "name": "Soco SD",
                "stream_url": "https://pull.niues.live/live/stream-9912052_lsd.m3u8?auth_key=1735574673-0-0-afefa8b5da2774df837bc4f9f28e6af5",
                "referer": "https://socolivev.co/"
            },
            {
                "name": "Soco HD",
                "stream_url": "https://pull.niues.live/live/stream-9912052_lhd.m3u8?auth_key=1735574673-0-0-141d513eabbfd781688694d8b3a2114e",
                "referer": "https://socolivev.co/"
            },
            {
                "name": "Soco SD",
                "stream_url": "https://pull.niues.live/live/stream-477560_lsd.m3u8?auth_key=1735515242-0-0-c9778bba8003a1090890fdb6d4c5ca10",
                "referer": "https://socolivev.co/"
            },
            {
                "name": "Soco HD",
                "stream_url": "https://pull.niues.live/live/stream-477560_lhd.m3u8?auth_key=1735515242-0-0-0d53bc70c3f35e078fc21b8f53c60290",
                "referer": "https://socolivev.co/"
            },
            {
                "name": "Soco SD",
                "stream_url": "https://pull.niues.live/live/stream-334434_lsd.m3u8?auth_key=1735574673-0-0-9643da2d9771d8692e40848f3ab7e263",
                "referer": "https://socolivev.co/"
            },
            {
                "name": "Soco HD",
                "stream_url": "https://pull.niues.live/live/stream-334434_lhd.m3u8?auth_key=1735574673-0-0-a7918ccbfbd257b5162a2ed468761f38",
                "referer": "https://socolivev.co/"
            }
        ]
    },
    {
        "match_time": "1735484400",
        "match_status": "live",
        "home_team_name": "Fulham",
        "home_team_logo": "https://sta.vnres.co/file/common/20241225/fee76d403eee176bec4ced79b2a85585.png",
        "away_team_name": "Bournemouth AFC",
        "away_team_logo": "https://sta.vnres.co/file/common/20241225/c030e7be219f980b6b6e46a90b6d12f4.png",
        "league_name": "ENG PR",
        "servers": [
            {
                "name": "Soco SD",
                "stream_url": "https://pull.niur.live/live/stream-356042_lsd.m3u8?txSecret=3083bc5c3e82d22bb2ea90fb923da276&txTime=67730ae1",
                "referer": "https://socolivev.co/"
            },
            {
                "name": "Soco HD",
                "stream_url": "https://pull.niur.live/live/stream-356042_lhd.m3u8?txSecret=1abaff46b9bb53767a6a6521dd1ce238&txTime=67730ae1",
                "referer": "https://socolivev.co/"
            },
            {
                "name": "Soco SD",
                "stream_url": "https://pull.niur.live/live/stream-9912101_lsd.m3u8?txSecret=5e0d794ccd5ee4b84dd748fea5257292&txTime=67730ae1",
                "referer": "https://socolivev.co/"
            },
            {
                "name": "Soco HD",
                "stream_url": "https://pull.niur.live/live/stream-9912101_lhd.m3u8?txSecret=00c277e1b34b8c9adb93d8b7b6f37ce8&txTime=67730ae1",
                "referer": "https://socolivev.co/"
            },
            {
                "name": "Soco SD",
                "stream_url": "https://pull.niues.live/live/stream-9912091_lsd.m3u8?auth_key=1735574673-0-0-dd767a837eb81d6c09ec8b778fe9b4e5",
                "referer": "https://socolivev.co/"
            },
            {
                "name": "Soco HD",
                "stream_url": "https://pull.niues.live/live/stream-9912091_lhd.m3u8?auth_key=1735574673-0-0-211e890f595b23dda6a0187303e3fe2b",
                "referer": "https://socolivev.co/"
            },
            {
                "name": "Soco SD",
                "stream_url": "https://pull.niues.live/live/stream-486629_lsd.m3u8?auth_key=1735502628-0-0-76036082770b6b7886c9c51458d74152",
                "referer": "https://socolivev.co/"
            },
            {
                "name": "Soco HD",
                "stream_url": "https://pull.niues.live/live/stream-486629_lhd.m3u8?auth_key=1735502628-0-0-c6abe4775d605b40b656e1f0084aacb2",
                "referer": "https://socolivev.co/"
            },
            {
                "name": "Soco SD",
                "stream_url": "https://pull.niues.live/live/stream-9912100_lsd.m3u8?auth_key=1735574673-0-0-d2f772c33ea8bb45b8d4458e783ff8f9",
                "referer": "https://socolivev.co/"
            },
            {
                "name": "Soco HD",
                "stream_url": "https://pull.niues.live/live/stream-9912100_lhd.m3u8?auth_key=1735574673-0-0-a84b9b3e6f797172a5610bc150e5fbca",
                "referer": "https://socolivev.co/"
            },
            {
                "name": "Soco SD",
                "stream_url": "https://pull.niues.live/live/stream-9912041_lsd.m3u8?auth_key=1735574673-0-0-a40e90a9ed8ad14f6044aa716c8e8dbf",
                "referer": "https://socolivev.co/"
            },
            {
                "name": "Soco HD",
                "stream_url": "https://pull.niues.live/live/stream-9912041_lhd.m3u8?auth_key=1735574673-0-0-4daa39927dcd2e5e87e04a454b6f5bbf",
                "referer": "https://socolivev.co/"
            }
        ]
    },
    {
        "match_time": "1735484400",
        "match_status": "live",
        "home_team_name": "Tottenham Hotspur",
        "home_team_logo": "https://sta.vnres.co/file/common/20241225/857ad33aabb19618a1c32a8de37d3bc3.png",
        "away_team_name": "Wolverhampton Wanderers",
        "away_team_logo": "https://sta.vnres.co/file/common/20241225/f2da5b8406910a58905d688c4872ff90.png",
        "league_name": "ENG PR",
        "servers": [
            {
                "name": "Soco SD",
                "stream_url": "https://pull.niur.live/live/stream-9912060_lsd.m3u8?txSecret=245d043946932ea818fc71f9014cdbcd&txTime=67730ae1",
                "referer": "https://socolivev.co/"
            },
            {
                "name": "Soco HD",
                "stream_url": "https://pull.niur.live/live/stream-9912060_lhd.m3u8?txSecret=a2212828f6a11ab4761f97b76cb6e7fb&txTime=67730ae1",
                "referer": "https://socolivev.co/"
            },
            {
                "name": "Soco SD",
                "stream_url": "https://pull.niur.live/live/stream-499765_lsd.m3u8?txSecret=7dc544bb5ab1830e8af78ced876ab572&txTime=67730ae1",
                "referer": "https://socolivev.co/"
            },
            {
                "name": "Soco HD",
                "stream_url": "https://pull.niur.live/live/stream-499765_lhd.m3u8?txSecret=05945262fb9fb8ffe52d36261674f671&txTime=67730ae1",
                "referer": "https://socolivev.co/"
            },
            {
                "name": "Soco SD",
                "stream_url": "https://pull.niues.live/live/stream-9912093_lsd.m3u8?auth_key=1735574673-0-0-b1b0bc83ec66d49c10da0e1508abc3ec",
                "referer": "https://socolivev.co/"
            },
            {
                "name": "Soco HD",
                "stream_url": "https://pull.niues.live/live/stream-9912093_lhd.m3u8?auth_key=1735574673-0-0-a6e1f37cb803ff8af1b478eb364b4338",
                "referer": "https://socolivev.co/"
            },
            {
                "name": "Soco SD",
                "stream_url": "https://pull.niues.live/live/stream-9912096_lsd.m3u8?auth_key=1735574673-0-0-5cfedb755893f5e5d732eb7f0af16d50",
                "referer": "https://socolivev.co/"
            },
            {
                "name": "Soco HD",
                "stream_url": "https://pull.niues.live/live/stream-9912096_lhd.m3u8?auth_key=1735574673-0-0-69a211dd87aacacdfdb6c3045d65807b",
                "referer": "https://socolivev.co/"
            },
            {
                "name": "Soco SD",
                "stream_url": "https://pull.niur.live/live/stream-256080_lsd.m3u8?txSecret=9f7c1193bff16f19c65d404c55a08eaf&txTime=67730ae1",
                "referer": "https://socolivev.co/"
            },
            {
                "name": "Soco HD",
                "stream_url": "https://pull.niur.live/live/stream-256080_lhd.m3u8?txSecret=fe2c369a1a9069cf357aae7da3d53a75&txTime=67730ae1",
                "referer": "https://socolivev.co/"
            },
            {
                "name": "Soco SD",
                "stream_url": "https://pull.niur.live/live/stream-9912048_lsd.m3u8?txSecret=f272b6b547c0db7db9d607da38ba33ce&txTime=67730ae1",
                "referer": "https://socolivev.co/"
            },
            {
                "name": "Soco HD",
                "stream_url": "https://pull.niur.live/live/stream-9912048_lhd.m3u8?txSecret=6d2c598a166716a13bcf3b0af2dabdba&txTime=67730ae1",
                "referer": "https://socolivev.co/"
            }
        ]
    },
    {
        "match_time": "1735484400",
        "match_status": "live",
        "home_team_name": "Stoke City",
        "home_team_logo": "https://sta.vnres.co/file/common/20241225/834c1ac5095fca404a486d5298ec6ecc.png",
        "away_team_name": "Sunderland",
        "away_team_logo": "https://sta.vnres.co/file/common/20241225/d2b8447920c1c3f3cadfc6cc555548bb.png",
        "league_name": "ENG LCH",
        "servers": [
            {
                "name": "Soco SD",
                "stream_url": "https://pull.niur.live/live/stream-291277_lsd.m3u8?txSecret=15fe8bceeb56e46c5fe1f8d4ca016969&txTime=67730a2c",
                "referer": "https://socolivev.co/"
            },
            {
                "name": "Soco HD",
                "stream_url": "https://pull.niur.live/live/stream-291277_lhd.m3u8?txSecret=1eae86dbe663f83c570d6e257a82b3d7&txTime=67730a2c",
                "referer": "https://socolivev.co/"
            },
            {
                "name": "Soco SD",
                "stream_url": "https://pull.niur.live/live/stream-484845_lsd.m3u8?txSecret=ccff12fed48c9031f232ffbe423fd352&txTime=6771f539",
                "referer": "https://socolivev.co/"
            },
            {
                "name": "Soco HD",
                "stream_url": "https://pull.niur.live/live/stream-484845_lhd.m3u8?txSecret=af02aafb43a3bbe14d4eb7bffe655b5e&txTime=6771f539",
                "referer": "https://socolivev.co/"
            }
        ]
    },
    {
        "match_time": "1735486200",
        "match_status": "live",
        "home_team_name": "Rio Ave",
        "home_team_logo": "https://sta.vnres.co/file/common/20241225/e7132937c807b7f5049b50b2a26b28f9.png",
        "away_team_name": "Nacional da Madeira",
        "away_team_logo": "https://sta.vnres.co/file/common/20241225/26e125db23c3b285dd00fe4573577573.gif",
        "league_name": "POR D1",
        "servers": [
            {
                "name": "Soco SD",
                "stream_url": "https://pull.niues.live/live/stream-493845_lsd.m3u8?auth_key=1735506420-0-0-585f9af47f6536ff6c1992e17bc0ecc9",
                "referer": "https://socolivev.co/"
            },
            {
                "name": "Soco HD",
                "stream_url": "https://pull.niues.live/live/stream-493845_lhd.m3u8?auth_key=1735506420-0-0-0a470ed834d3bd659f770ed80a8dd684",
                "referer": "https://socolivev.co/"
            },
            {
                "name": "Soco SD",
                "stream_url": "https://pull.niur.live/live/stream-400722_lsd.m3u8?txSecret=ee41bcb9accde76bc2ac3babbdc1f00b&txTime=677204f2",
                "referer": "https://socolivev.co/"
            },
            {
                "name": "Soco HD",
                "stream_url": "https://pull.niur.live/live/stream-400722_lhd.m3u8?txSecret=981c17104ffe1cc320a687f6f77d6691&txTime=677204f2",
                "referer": "https://socolivev.co/"
            }
        ]
    },
    {
        "match_time": "1735486200",
        "match_status": "live",
        "home_team_name": "SC Farense",
        "home_team_logo": "https://sta.vnres.co/file/common/20241225/a63a5474f85fc6ed55c7a1311ff097c6.png",
        "away_team_name": "Vitoria Guimaraes",
        "away_team_logo": "https://sta.vnres.co/file/common/20241225/8f73af22e056d3a33ec0fc48b948d32c.png",
        "league_name": "POR D1",
        "servers": [
            {
                "name": "Soco SD",
                "stream_url": "https://pull.niues.live/live/stream-494201_lsd.m3u8?auth_key=1735506152-0-0-128ac554a8510347a4b12e4feaa10233",
                "referer": "https://socolivev.co/"
            },
            {
                "name": "Soco HD",
                "stream_url": "https://pull.niues.live/live/stream-494201_lhd.m3u8?auth_key=1735506152-0-0-ba4408879f42545aeb245e773541f2a3",
                "referer": "https://socolivev.co/"
            },
            {
                "name": "Soco SD",
                "stream_url": "https://pull.niues.live/live/stream-329740_lsd.m3u8?auth_key=1735512966-0-0-1af040b05553651eb5f95450dbc20f76",
                "referer": "https://socolivev.co/"
            },
            {
                "name": "Soco HD",
                "stream_url": "https://pull.niues.live/live/stream-329740_lhd.m3u8?auth_key=1735512966-0-0-a6193008e9a254d197b01c52c8201643",
                "referer": "https://socolivev.co/"
            }
        ]
    },
    {
        "match_time": "1735487100",
        "match_status": "live",
        "home_team_name": "Al Nasr Dubai",
        "home_team_logo": "https://sta.vnres.co/file/common/20241225/c3d887c49c8883c3b8f657367ff8116d.png",
        "away_team_name": "Shabab AlAhli",
        "away_team_logo": "https://sta.vnres.co/file/common/20241225/18d53b3a3baccb2a9f4ef1fe8f03920d.png",
        "league_name": "UAE EC",
        "servers": [
            {
                "name": "Soco SD",
                "stream_url": "https://pull.niur.live/live/stream-336303_lsd.m3u8?txSecret=e9017d6ba0b081b95ec4b0d6627f6f85&txTime=677200d7",
                "referer": "https://socolivev.co/"
            },
            {
                "name": "Soco HD",
                "stream_url": "https://pull.niur.live/live/stream-336303_lhd.m3u8?txSecret=1e691175c146212a5f6a8113be1efa6b&txTime=677200d7",
                "referer": "https://socolivev.co/"
            },
            {
                "name": "Soco SD",
                "stream_url": "https://pull.niur.live/live/stream-445260_lsd.m3u8?txSecret=62b6a128e450977cf6fb889f17996cfc&txTime=67722c82",
                "referer": "https://socolivev.co/"
            },
            {
                "name": "Soco HD",
                "stream_url": "https://pull.niur.live/live/stream-445260_lhd.m3u8?txSecret=dabe1f5badd804886e88575454a65c3e&txTime=67722c82",
                "referer": "https://socolivev.co/"
            }
        ]
    },
    {
        "match_time": "1735567200",
        "match_status": "live",
        "home_team_name": "Thailand",
        "home_team_logo": "https://sta.vnres.co/file/common/20241225/e317867627ecba89ea9043732404c1f1.png",
        "away_team_name": "Philippines",
        "away_team_logo": "https://sta.vnres.co/file/common/20241225/ba727d4817dee286161492a1163bc2f3.png",
        "league_name": "AFF SC",
        "servers": [
            {
                "name": "Soco SD",
                "stream_url": "https://pull.niues.live/live/stream-9912100_lsd.m3u8?auth_key=1735574673-0-0-d2f772c33ea8bb45b8d4458e783ff8f9",
                "referer": "https://socolivev.co/"
            },
            {
                "name": "Soco HD",
                "stream_url": "https://pull.niues.live/live/stream-9912100_lhd.m3u8?auth_key=1735574673-0-0-a84b9b3e6f797172a5610bc150e5fbca",
                "referer": "https://socolivev.co/"
            },
            {
                "name": "Soco SD",
                "stream_url": "https://pull.niues.live/live/stream-9912041_lsd.m3u8?auth_key=1735574673-0-0-a40e90a9ed8ad14f6044aa716c8e8dbf",
                "referer": "https://socolivev.co/"
            },
            {
                "name": "Soco HD",
                "stream_url": "https://pull.niues.live/live/stream-9912041_lhd.m3u8?auth_key=1735574673-0-0-4daa39927dcd2e5e87e04a454b6f5bbf",
                "referer": "https://socolivev.co/"
            },
            {
                "name": "Soco SD",
                "stream_url": "https://pull.niur.live/live/stream-9912060_lsd.m3u8?txSecret=245d043946932ea818fc71f9014cdbcd&txTime=67730ae1",
                "referer": "https://socolivev.co/"
            },
            {
                "name": "Soco HD",
                "stream_url": "https://pull.niur.live/live/stream-9912060_lhd.m3u8?txSecret=a2212828f6a11ab4761f97b76cb6e7fb&txTime=67730ae1",
                "referer": "https://socolivev.co/"
            },
            {
                "name": "Soco SD",
                "stream_url": "https://pull.niur.live/live/stream-499765_lsd.m3u8?txSecret=7dc544bb5ab1830e8af78ced876ab572&txTime=67730ae1",
                "referer": "https://socolivev.co/"
            },
            {
                "name": "Soco HD",
                "stream_url": "https://pull.niur.live/live/stream-499765_lhd.m3u8?txSecret=05945262fb9fb8ffe52d36261674f671&txTime=67730ae1",
                "referer": "https://socolivev.co/"
            },
            {
                "name": "Soco SD",
                "stream_url": "https://pull.niues.live/live/stream-9912091_lsd.m3u8?auth_key=1735574673-0-0-dd767a837eb81d6c09ec8b778fe9b4e5",
                "referer": "https://socolivev.co/"
            },
            {
                "name": "Soco HD",
                "stream_url": "https://pull.niues.live/live/stream-9912091_lhd.m3u8?auth_key=1735574673-0-0-211e890f595b23dda6a0187303e3fe2b",
                "referer": "https://socolivev.co/"
            },
            {
                "name": "Soco SD",
                "stream_url": "https://pull.niues.live/live/stream-9912096_lsd.m3u8?auth_key=1735574673-0-0-5cfedb755893f5e5d732eb7f0af16d50",
                "referer": "https://socolivev.co/"
            },
            {
                "name": "Soco HD",
                "stream_url": "https://pull.niues.live/live/stream-9912096_lhd.m3u8?auth_key=1735574673-0-0-69a211dd87aacacdfdb6c3045d65807b",
                "referer": "https://socolivev.co/"
            },
            {
                "name": "Soco SD",
                "stream_url": "https://pull.niur.live/live/stream-9912048_lsd.m3u8?txSecret=f272b6b547c0db7db9d607da38ba33ce&txTime=67730ae1",
                "referer": "https://socolivev.co/"
            },
            {
                "name": "Soco HD",
                "stream_url": "https://pull.niur.live/live/stream-9912048_lhd.m3u8?txSecret=6d2c598a166716a13bcf3b0af2dabdba&txTime=67730ae1",
                "referer": "https://socolivev.co/"
            },
            {
                "name": "Soco SD",
                "stream_url": "https://pull.niues.live/live/stream-9912052_lsd.m3u8?auth_key=1735574673-0-0-afefa8b5da2774df837bc4f9f28e6af5",
                "referer": "https://socolivev.co/"
            },
            {
                "name": "Soco HD",
                "stream_url": "https://pull.niues.live/live/stream-9912052_lhd.m3u8?auth_key=1735574673-0-0-141d513eabbfd781688694d8b3a2114e",
                "referer": "https://socolivev.co/"
            },
            {
                "name": "Soco SD",
                "stream_url": "https://pull.niur.live/live/stream-9912101_lsd.m3u8?txSecret=5e0d794ccd5ee4b84dd748fea5257292&txTime=67730ae1",
                "referer": "https://socolivev.co/"
            },
            {
                "name": "Soco HD",
                "stream_url": "https://pull.niur.live/live/stream-9912101_lhd.m3u8?txSecret=00c277e1b34b8c9adb93d8b7b6f37ce8&txTime=67730ae1",
                "referer": "https://socolivev.co/"
            },
            {
                "name": "Soco SD",
                "stream_url": "https://pull.niues.live/live/stream-9912093_lsd.m3u8?auth_key=1735574673-0-0-b1b0bc83ec66d49c10da0e1508abc3ec",
                "referer": "https://socolivev.co/"
            },
            {
                "name": "Soco HD",
                "stream_url": "https://pull.niues.live/live/stream-9912093_lhd.m3u8?auth_key=1735574673-0-0-a6e1f37cb803ff8af1b478eb364b4338",
                "referer": "https://socolivev.co/"
            },
            {
                "name": "Soco SD",
                "stream_url": "https://pull.niues.live/live/stream-299144_lsd.m3u8?auth_key=1735574673-0-0-e80c51c9ed5721db3625de54db7a9c68",
                "referer": "https://socolivev.co/"
            },
            {
                "name": "Soco HD",
                "stream_url": "https://pull.niues.live/live/stream-299144_lhd.m3u8?auth_key=1735574673-0-0-238e701fd9b398b8e864c37bb56d0dc3",
                "referer": "https://socolivev.co/"
            },
            {
                "name": "Soco SD",
                "stream_url": "https://pull.niur.live/live/stream-256080_lsd.m3u8?txSecret=9f7c1193bff16f19c65d404c55a08eaf&txTime=67730ae1",
                "referer": "https://socolivev.co/"
            },
            {
                "name": "Soco HD",
                "stream_url": "https://pull.niur.live/live/stream-256080_lhd.m3u8?txSecret=fe2c369a1a9069cf357aae7da3d53a75&txTime=67730ae1",
                "referer": "https://socolivev.co/"
            }
        ]
    },
    {
        "match_time": "1735567200",
        "match_status": "live",
        "home_team_name": "Mumbai City FC",
        "home_team_logo": "https://sta.vnres.co/file/common/20241225/b0ec058dcdfd8309d0d3e732e949c897.png",
        "away_team_name": "Northeast United",
        "away_team_logo": "https://sta.vnres.co/file/common/20241225/89f819c67fa4d86064d06f7cbc60d3cc.png",
        "league_name": "IND SL",
        "servers": [
            {
                "name": "Soco SD",
                "stream_url": "https://pull.niues.live/live/stream-406865_lsd.m3u8?auth_key=1735574673-0-0-25fab75b932964d570de2572500cd191",
                "referer": "https://socolivev.co/"
            },
            {
                "name": "Soco HD",
                "stream_url": "https://pull.niues.live/live/stream-406865_lhd.m3u8?auth_key=1735574673-0-0-68f423e1ad8e6d57733c5beb16638746",
                "referer": "https://socolivev.co/"
            },
            {
                "name": "Soco SD",
                "stream_url": "https://pull.niues.live/live/stream-304148_lsd.m3u8?auth_key=1735574673-0-0-ec6ea629ecb5348cbba8b6d2142a1a5b",
                "referer": "https://socolivev.co/"
            },
            {
                "name": "Soco HD",
                "stream_url": "https://pull.niues.live/live/stream-304148_lhd.m3u8?auth_key=1735574673-0-0-219859c43aabc4fda94e3225562b1b33",
                "referer": "https://socolivev.co/"
            },
            {
                "name": "Soco SD",
                "stream_url": "https://pull.niues.live/live/stream-472241_lsd.m3u8?auth_key=1735574673-0-0-d388daa430a6458131d61ff993c67514",
                "referer": "https://socolivev.co/"
            },
            {
                "name": "Soco HD",
                "stream_url": "https://pull.niues.live/live/stream-472241_lhd.m3u8?auth_key=1735574673-0-0-51489655a65210f66031374baffa5225",
                "referer": "https://socolivev.co/"
            },
            {
                "name": "Soco SD",
                "stream_url": "https://pull.niues.live/live/stream-380460_lsd.m3u8?auth_key=1735574673-0-0-29e1b94cff6ef4e639a3b894976a58bd",
                "referer": "https://socolivev.co/"
            },
            {
                "name": "Soco HD",
                "stream_url": "https://pull.niues.live/live/stream-380460_lhd.m3u8?auth_key=1735574673-0-0-2fb123ae4ad41ba1c94650e4dbf30207",
                "referer": "https://socolivev.co/"
            },
            {
                "name": "Soco SD",
                "stream_url": "https://pull.niues.live/live/stream-474421_lsd.m3u8?auth_key=1735574673-0-0-c4e9bff6953c2cce57d1ff70e98722be",
                "referer": "https://socolivev.co/"
            },
            {
                "name": "Soco HD",
                "stream_url": "https://pull.niues.live/live/stream-474421_lhd.m3u8?auth_key=1735574673-0-0-6e8827a660e9c4fca2cfddc8cf2946c8",
                "referer": "https://socolivev.co/"
            },
            {
                "name": "Soco SD",
                "stream_url": "https://pull.niues.live/live/stream-381230_lsd.m3u8?auth_key=1735574673-0-0-d6e08203719bdae3f3b5f5c0ab3c0d4d",
                "referer": "https://socolivev.co/"
            },
            {
                "name": "Soco HD",
                "stream_url": "https://pull.niues.live/live/stream-381230_lhd.m3u8?auth_key=1735574673-0-0-edb09b6b7f976ae46f4aabc8d55a29cc",
                "referer": "https://socolivev.co/"
            }
        ]
    },
    {
        "match_time": "1735570800",
        "match_status": "live",
        "home_team_name": "El Gounah",
        "home_team_logo": "https://sta.vnres.co/file/common/20241225/8ac404a798280673c16ca89d44c2baf0.png",
        "away_team_name": "Pyramids FC",
        "away_team_logo": "https://sta.vnres.co/file/common/20241225/7160cb5178bfff0e8d6a68ba0bd9e16a.png",
        "league_name": "EGY D1",
        "servers": [
            {
                "name": "Soco SD",
                "stream_url": "https://pull.niues.live/live/stream-434982_lsd.m3u8?auth_key=1735574673-0-0-5027a6813665d99694256c88b5d2fae1",
                "referer": "https://socolivev.co/"
            },
            {
                "name": "Soco HD",
                "stream_url": "https://pull.niues.live/live/stream-434982_lhd.m3u8?auth_key=1735574673-0-0-5e5459d6afaca81b130ad0cea802a009",
                "referer": "https://socolivev.co/"
            },
            {
                "name": "Soco SD",
                "stream_url": "https://pull.niues.live/live/stream-334434_lsd.m3u8?auth_key=1735574673-0-0-9643da2d9771d8692e40848f3ab7e263",
                "referer": "https://socolivev.co/"
            },
            {
                "name": "Soco HD",
                "stream_url": "https://pull.niues.live/live/stream-334434_lhd.m3u8?auth_key=1735574673-0-0-a7918ccbfbd257b5162a2ed468761f38",
                "referer": "https://socolivev.co/"
            },
            {
                "name": "Soco SD",
                "stream_url": "https://pull.niues.live/live/stream-9912050_lsd.m3u8?auth_key=1735574673-0-0-4af1bf63e28201f92e60c8efada8564d",
                "referer": "https://socolivev.co/"
            },
            {
                "name": "Soco HD",
                "stream_url": "https://pull.niues.live/live/stream-9912050_lhd.m3u8?auth_key=1735574673-0-0-42b0c53ddc4545219fe4f0064843ee64",
                "referer": "https://socolivev.co/"
            },
            {
                "name": "Soco SD",
                "stream_url": "https://pull.niues.live/live/stream-414317_lsd.m3u8?auth_key=1735574673-0-0-f393c419ba530a181030558480e6815a",
                "referer": "https://socolivev.co/"
            },
            {
                "name": "Soco HD",
                "stream_url": "https://pull.niues.live/live/stream-414317_lhd.m3u8?auth_key=1735574673-0-0-616b22ef00ec71baabf451e40a1cf36f",
                "referer": "https://socolivev.co/"
            },
            {
                "name": "Soco SD",
                "stream_url": "https://pull.niues.live/live/stream-479849_lsd.m3u8?auth_key=1735574673-0-0-dc460c325e498128411c34e0a1b804bc",
                "referer": "https://socolivev.co/"
            },
            {
                "name": "Soco HD",
                "stream_url": "https://pull.niues.live/live/stream-479849_lhd.m3u8?auth_key=1735574673-0-0-57eea777f5d7e5f304037325dcf99dc6",
                "referer": "https://socolivev.co/"
            },
            {
                "name": "Soco SD",
                "stream_url": "https://pull.niues.live/live/stream-9912097_lsd.m3u8?auth_key=1735574673-0-0-d6cfc991ce4182f874646eb2e8232131",
                "referer": "https://socolivev.co/"
            },
            {
                "name": "Soco HD",
                "stream_url": "https://pull.niues.live/live/stream-9912097_lhd.m3u8?auth_key=1735574673-0-0-4b407952457e6b9a9dd58e27edf3db19",
                "referer": "https://socolivev.co/"
            }
        ]
    },
    {
        "match_time": "1735570800",
        "match_status": "live",
        "home_team_name": "Enppi",
        "home_team_logo": "https://sta.vnres.co/file/common/20241225/b066f228683b0df38f45fe717e37e8c1.png",
        "away_team_name": "El Ahly Cairo",
        "away_team_logo": "https://sta.vnres.co/file/common/20241225/45c607fce446210bdaaa3fc66e7398b8.png",
        "league_name": "EGY D1",
        "servers": [
            {
                "name": "Soco SD",
                "stream_url": "https://pull.niues.live/live/stream-9912008_lsd.m3u8?auth_key=1735574673-0-0-ceee009149691dba6cb8853c4a896aa2",
                "referer": "https://socolivev.co/"
            },
            {
                "name": "Soco HD",
                "stream_url": "https://pull.niues.live/live/stream-9912008_lhd.m3u8?auth_key=1735574673-0-0-51b9596d05476a28e89cec0e93ece23d",
                "referer": "https://socolivev.co/"
            },
            {
                "name": "Soco SD",
                "stream_url": "https://pull.niues.live/live/stream-313971_lsd.m3u8?auth_key=1735574673-0-0-8beb5e896c8b9f669d214aec0f7cc907",
                "referer": "https://socolivev.co/"
            },
            {
                "name": "Soco HD",
                "stream_url": "https://pull.niues.live/live/stream-313971_lhd.m3u8?auth_key=1735574673-0-0-61ec2dffd5d280b954100ef556b7b0e3",
                "referer": "https://socolivev.co/"
            },
            {
                "name": "Soco SD",
                "stream_url": "https://pull.niues.live/live/stream-991140_lsd.m3u8?auth_key=1735574673-0-0-fe863604770fa340f16193764a8e7702",
                "referer": "https://socolivev.co/"
            },
            {
                "name": "Soco HD",
                "stream_url": "https://pull.niues.live/live/stream-991140_lhd.m3u8?auth_key=1735574673-0-0-ea656d87c65863a4ac843ecb51258edf",
                "referer": "https://socolivev.co/"
            },
            {
                "name": "Soco SD",
                "stream_url": "https://pull.niues.live/live/stream-9912015_lsd.m3u8?auth_key=1735574673-0-0-25c8344fb2c8bf76477a4bbfadb2cf36",
                "referer": "https://socolivev.co/"
            },
            {
                "name": "Soco HD",
                "stream_url": "https://pull.niues.live/live/stream-9912015_lhd.m3u8?auth_key=1735574673-0-0-6b9778a83705bc3c19223d600ea621f2",
                "referer": "https://socolivev.co/"
            },
            {
                "name": "Soco SD",
                "stream_url": "https://pull.niur.live/live/stream-356042_lsd.m3u8?txSecret=3083bc5c3e82d22bb2ea90fb923da276&txTime=67730ae1",
                "referer": "https://socolivev.co/"
            },
            {
                "name": "Soco HD",
                "stream_url": "https://pull.niur.live/live/stream-356042_lhd.m3u8?txSecret=1abaff46b9bb53767a6a6521dd1ce238&txTime=67730ae1",
                "referer": "https://socolivev.co/"
            },
            {
                "name": "Soco SD",
                "stream_url": "https://pull.niur.live/live/stream-9912009_lsd.m3u8?txSecret=b9bf33979a4a432f1fe88f570a54b91f&txTime=67730ae1",
                "referer": "https://socolivev.co/"
            },
            {
                "name": "Soco HD",
                "stream_url": "https://pull.niur.live/live/stream-9912009_lhd.m3u8?txSecret=a20fa77469ff2068c20bec7ab7316ab8&txTime=67730ae1",
                "referer": "https://socolivev.co/"
            }
        ]
    },
    {
        "match_time": "1735573500",
        "match_status": "vs",
        "home_team_name": "Al-Jazira(UAE)",
        "home_team_logo": "https://sta.vnres.co/file/common/20241225/262f236e8659964aae4d1ba0d35ba4bb.png",
        "away_team_name": "Al-Ain FC",
        "away_team_logo": "https://sta.vnres.co/file/common/20241225/b30cd953fa7542e7c5e0cee51f491a3f.jpg",
        "league_name": "UAE EC",
        "servers": []
    },
    {
        "match_time": "1735578000",
        "match_status": "vs",
        "home_team_name": "Valencia",
        "home_team_logo": "https://sta.vnres.co/file/common/20241229/7a00fb2a871f78a6502dbf5137073ad8.png",
        "away_team_name": "Forca Lleida",
        "away_team_logo": "https://sta.vnres.co/file/common/20241229/37e6ce6bb1965f1fb93fb335f107197f.png",
        "league_name": "ACB",
        "servers": []
    },
    {
        "match_time": "1735579800",
        "match_status": "vs",
        "home_team_name": "Como",
        "home_team_logo": "https://sta.vnres.co/file/common/20241228/dc4b8f1d6943d3243dbbcb3c6fe0f326.png",
        "away_team_name": "Lecce",
        "away_team_logo": "https://sta.vnres.co/file/common/20241228/f5309d812f595ddf1005684eaa6a6703.png",
        "league_name": "ITA D1",
        "servers": []
    },
    {
        "match_time": "1735581600",
        "match_status": "vs",
        "home_team_name": "Pharco",
        "home_team_logo": "https://sta.vnres.co/file/common/20241228/2dce2a3608e99c9d1e3cabc086136ad8.png",
        "away_team_name": "Smouha SC",
        "away_team_logo": "https://sta.vnres.co/file/common/20241228/b927795b31f336e6c781a0feecc8ef64.png",
        "league_name": "EGY D1",
        "servers": []
    },
    {
        "match_time": "1735581600",
        "match_status": "vs",
        "home_team_name": "ZED FC",
        "home_team_logo": "https://sta.vnres.co/file/common/20241228/af6f8bcfb10b2f8bc3d3cfbd8e41040f.png",
        "away_team_name": "Petrojet",
        "away_team_logo": "https://sta.vnres.co/file/common/20241228/2714b89330baa54676b1d4e6445e4d5c.png",
        "league_name": "EGY D1",
        "servers": []
    },
    {
        "match_time": "1735587900",
        "match_status": "vs",
        "home_team_name": "Bologna",
        "home_team_logo": "https://sta.vnres.co/file/common/20241228/c256517d2b126e9c27bbf15534a49dd3.png",
        "away_team_name": "Hellas Verona",
        "away_team_logo": "https://sta.vnres.co/file/common/20241228/c42334ce51ecdf23eb5820bcc76be201.png",
        "league_name": "ITA D1",
        "servers": []
    },
    {
        "match_time": "1735587900",
        "match_status": "vs",
        "home_team_name": "Aston Villa",
        "home_team_logo": "https://sta.vnres.co/file/common/20241228/542381920ed5db2e0af0203a02472c0f.png",
        "away_team_name": "Brighton Hove Albion",
        "away_team_logo": "https://sta.vnres.co/file/common/20241228/cf1113b571013b1dd4ce0e7bebe076e0.png",
        "league_name": "ENG PR",
        "servers": []
    },
    {
        "match_time": "1735587900",
        "match_status": "vs",
        "home_team_name": "Ipswich Town",
        "home_team_logo": "https://sta.vnres.co/file/common/20241228/9d221b22dcd3239108f007440eb6da02.png",
        "away_team_name": "Chelsea",
        "away_team_logo": "https://sta.vnres.co/file/common/20241228/e01fabb79ce42701962950b873b5be5d.png",
        "league_name": "ENG PR",
        "servers": []
    },
    {
        "match_time": "1735588800",
        "match_status": "vs",
        "home_team_name": "Manchester United",
        "home_team_logo": "https://sta.vnres.co/file/common/20241228/3f7a867a7297ffc8f146cc5c04c6c472.png",
        "away_team_name": "Newcastle United",
        "away_team_logo": "https://sta.vnres.co/file/common/20241228/2d201f10cd4ca9a1b72f818e9ef43605.png",
        "league_name": "ENG PR",
        "servers": []
    },
    {
        "match_time": "1735588800",
        "match_status": "vs",
        "home_team_name": "AFC Wimbledon",
        "home_team_logo": "https://sta.vnres.co/file/common/20241228/ed75d43770c49f52459e7d6c8ec6380c.png",
        "away_team_name": "Gillingham",
        "away_team_logo": "https://sta.vnres.co/file/common/20241228/78ef621731b6cc5f6c50a946ec53e5d3.png",
        "league_name": "ENG D2",
        "servers": []
    },
    {
        "match_time": "1735589700",
        "match_status": "vs",
        "home_team_name": "FC Famalicao",
        "home_team_logo": "https://sta.vnres.co/file/common/20241228/c6fd2f365dffd401cd12511b57b77ff9.png",
        "away_team_name": "Santa Clara",
        "away_team_logo": "https://sta.vnres.co/file/common/20241228/c7c9930d3d9d8e410244ac92594e9057.png",
        "league_name": "POR D1",
        "servers": []
    },
    {
        "match_time": "1735603200",
        "match_status": "vs",
        "home_team_name": "Charlotte Hornets",
        "home_team_logo": "https://sta.vnres.co/file/common/20241229/ef9f33ad44b89b0157b27aaf6e6e63f3.png",
        "away_team_name": "Chicago Bulls",
        "away_team_logo": "https://sta.vnres.co/file/common/20241229/72a02304c751dc4fd13f71cd5878398e.png",
        "league_name": "NBA",
        "servers": []
    },
    {
        "match_time": "1735603200",
        "match_status": "vs",
        "home_team_name": "Washington Wizards",
        "home_team_logo": "https://sta.vnres.co/file/common/20241229/f2f1947f29df5529752a5a6ebcaab085.png",
        "away_team_name": "New York Knicks",
        "away_team_logo": "https://sta.vnres.co/file/common/20241229/ee13f6d016a5dcbd8c2b77b975b56abf.png",
        "league_name": "NBA",
        "servers": []
    },
    {
        "match_time": "1735614000",
        "match_status": "vs",
        "home_team_name": "Golden State Warriors",
        "home_team_logo": "https://sta.vnres.co/file/common/20241229/8c02339e76eac4eae88ae8b3feb8c9fe.png",
        "away_team_name": "Cleveland Cavaliers",
        "away_team_logo": "https://sta.vnres.co/file/common/20241229/496943eec67e888ad09c2455bc735175.png",
        "league_name": "NBA",
        "servers": []
    },
    {
        "match_time": "1735614000",
        "match_status": "vs",
        "home_team_name": "Portland Trail Blazers",
        "home_team_logo": "https://sta.vnres.co/file/common/20241229/df0d8a066e7f4d23261639fa89b89dc5.png",
        "away_team_name": "Philadelphia 76ers",
        "away_team_logo": "https://sta.vnres.co/file/common/20241229/322bcc908f43d337e1d238ef1f753454.png",
        "league_name": "NBA",
        "servers": []
    },
    {
        "match_time": "1735614000",
        "match_status": "vs",
        "home_team_name": "Sacramento Kings",
        "home_team_logo": "https://sta.vnres.co/file/common/20241229/be12ed5be32e776108e6d16647ea9881.png",
        "away_team_name": "Dallas Mavericks",
        "away_team_logo": "https://sta.vnres.co/file/common/20241229/8e492d8dd3c9e5ad3251652dab0514f3.png",
        "league_name": "NBA",
        "servers": []
    },
    {
        "match_time": "1735622100",
        "match_status": "vs",
        "home_team_name": "Central Coast Mariners (w)",
        "home_team_logo": "https://sta.vnres.co/file/common/20241228/40ef590b54c57f80451574b291ef7b04.png",
        "away_team_name": "Melbourne City (w)",
        "away_team_logo": "https://sta.vnres.co/file/common/20241228/deaa25512d8551ec473024cb70edbd19.png",
        "league_name": "AUS WAL",
        "servers": []
    },
    {
        "match_time": "1735626600",
        "match_status": "vs",
        "home_team_name": "Illawarra Hawks",
        "home_team_logo": "https://sta.vnres.co/file/common/20241229/8d1337253d3e7627d238a49b57abf7aa.png",
        "away_team_name": "South East Melbourne",
        "away_team_logo": "https://sta.vnres.co/file/common/20241229/4521eeb9ef86bba70fcf9386950d4115.png",
        "league_name": "NBL",
        "servers": []
    },
    {
        "match_time": "1735632000",
        "match_status": "vs",
        "home_team_name": "Central Coast Mariners",
        "home_team_logo": "https://sta.vnres.co/file/common/20241228/7fb6723974c52a3d758602439437bc6c.png",
        "away_team_name": "Melbourne City",
        "away_team_logo": "https://sta.vnres.co/file/common/20241228/d5acd5869ec2b3b879fdbcea661d83a8.png",
        "league_name": "AUS D1",
        "servers": []
    },
    {
        "match_time": "1735633800",
        "match_status": "vs",
        "home_team_name": "Bangladesh Police Club",
        "home_team_logo": "https://sta.vnres.co/file/common/20241230/728bd2d48b536878f60791e2f859d7e6.png",
        "away_team_name": "Bashundhara Kings",
        "away_team_logo": "https://sta.vnres.co/file/common/20241230/40039169cfe6b5dd6073973b800017a2.png",
        "league_name": "BAN FCup",
        "servers": []
    },
    {
        "match_time": "1735633800",
        "match_status": "vs",
        "home_team_name": "Fortis Limited",
        "home_team_logo": "https://sta.vnres.co/file/common/20241230/f2e7ab3403ca0d20eaf61f439ff6942a.png",
        "away_team_name": "Dhaka Wanderers",
        "away_team_logo": "https://sta.vnres.co/file/common/20241230/e4d1e4847d3ab8577d3052cc9be33e3e.png",
        "league_name": "BAN FCup",
        "servers": []
    },
    {
        "match_time": "1735633800",
        "match_status": "vs",
        "home_team_name": "Cairns Taipans",
        "home_team_logo": "https://sta.vnres.co/file/common/20241229/0867f87f3216613aa5a5af69bd2cae08.png",
        "away_team_name": "New Zealand Breakers",
        "away_team_logo": "https://sta.vnres.co/file/common/20241229/2ed9cc21154b1d66c832d643aeb0a850.png",
        "league_name": "NBL",
        "servers": []
    },
    {
        "match_time": "1735635600",
        "match_status": "vs",
        "home_team_name": "Townsville W",
        "home_team_logo": "https://sta.vnres.co/file/common/20241229/e731638b618650c3f41a804e3d1b6c75.png",
        "away_team_name": "Bendigo W",
        "away_team_logo": "https://sta.vnres.co/file/common/20241229/06d720969028eaf27d91d06f448b5fb0.png",
        "league_name": "WNBL",
        "servers": []
    },
    {
        "match_time": "1735644900",
        "match_status": "vs",
        "home_team_name": "Fujian",
        "home_team_logo": "https://sta.vnres.co/file/common/20241229/d9a78188ce27325af1c93e4a8038b206.png",
        "away_team_name": "Jiangsu Dragons",
        "away_team_logo": "https://sta.vnres.co/file/common/20241229/7bcbcd44ea8ce798324074ea5a228417.png",
        "league_name": "CBA",
        "servers": []
    },
    {
        "match_time": "1735650000",
        "match_status": "vs",
        "home_team_name": "Ceramica Cleopatra FC",
        "home_team_logo": "https://sta.vnres.co/file/common/20241228/ae2c5fdb4ae626a027ea38c9eb4db095.png",
        "away_team_name": "Al Masry",
        "away_team_logo": "https://sta.vnres.co/file/common/20241228/74013ecfc4b7ca4e2d76621ea7b53c98.png",
        "league_name": "EGY D1",
        "servers": []
    },
    {
        "match_time": "1735650000",
        "match_status": "vs",
        "home_team_name": "Alba Berlin",
        "home_team_logo": "https://sta.vnres.co/file/common/20241229/d577b3067a1d674a02d25e8b8d26b098.png",
        "away_team_name": "Rostock",
        "away_team_logo": "https://sta.vnres.co/file/common/20241229/d2b7c6987d156334c2a17c3228086d48.png",
        "league_name": "GBBL",
        "servers": []
    },
    {
        "match_time": "1735650000",
        "match_status": "vs",
        "home_team_name": "Mobis Phoebus",
        "home_team_logo": "https://sta.vnres.co/file/common/20241229/8bca4fbebe51bb264e9155463ed897f0.png",
        "away_team_name": "KoGas",
        "away_team_logo": "https://sta.vnres.co/file/common/20241229/0329ec48b5119dabbb0727da4958c106.png",
        "league_name": "KBL",
        "servers": []
    },
    {
        "match_time": "1735657200",
        "match_status": "vs",
        "home_team_name": "Solihull Moors",
        "home_team_logo": "https://sta.vnres.co/file/common/20241228/c6687762cac5a08c1bfff8f9c27ea708.png",
        "away_team_name": "Tamworth",
        "away_team_logo": "https://sta.vnres.co/file/common/20241228/6ff832ce2bb6cb2b20286d478b96edcb.png",
        "league_name": "ENG Conf",
        "servers": []
    },
    {
        "match_time": "1735657200",
        "match_status": "vs",
        "home_team_name": "Scunthorpe United",
        "home_team_logo": "https://sta.vnres.co/file/common/20241228/04ea837f850292fb84735c39df0d8b75.png",
        "away_team_name": "Kings Lynn",
        "away_team_logo": "https://sta.vnres.co/file/common/20241228/c4a1a53df1a613ed563bd00f298262a7.png",
        "league_name": "ENG CN",
        "servers": []
    }
]